{
  "metadata": {
    "step": "R-04",
    "extracted_at": "2025-11-21T19:32:31.309378",
    "source_file": "E:\\devSpace\\SpringBootProjects\\wherehouse_SpringBoot-master\\wherehouse\\log\\wherehouse.log",
    "total_logs": 40,
    "end_logs": 20,
    "output_file": "r04_parsed_data.json"
  },
  "logs": [
    {
      "timestamp": "2025-11-21T10:20:34.152205300Z",
      "nanoTime": 26020166357800,
      "traceId": "5d95222b",
      "thread": "http-nio-8185-exec-2",
      "eventType": "PERFORMANCE",
      "step": "R-04",
      "layer": "Service",
      "class": "LocationAnalysisServiceImpl",
      "method": "performExternalApiCalls",
      "action": "performExternalApiCalls",
      "status": "START"
    },
    {
      "timestamp": "2025-11-21T10:20:35.803907200Z",
      "nanoTime": 26021818311700,
      "traceId": "5d95222b",
      "thread": "http-nio-8185-exec-2",
      "eventType": "PERFORMANCE",
      "step": "R-04",
      "layer": "Service",
      "class": "LocationAnalysisServiceImpl",
      "method": "performExternalApiCalls",
      "action": "performExternalApiCalls",
      "status": "END",
      "duration_ns": 1651953900,
      "duration_ms": 1651,
      "resultData": {
        "latitude": 37.4979,
        "longitude": 127.0276,
        "radius": 500,
        "totalSequentialTasks": 3,
        "totalExecutionTimeNs": 1648314100,
        "addressApiResult": {
          "cached": false,
          "cacheKey": "address:37.4979:127.0276",
          "roadAddress": "주소 없음",
          "jibunAddress": "서울 서초구 서초동 1373",
          "responseSize": 58,
          "executionTimeNs": 574176300,
          "errorMessage": null,
          "success": true
        },
        "arrestRateResult": {
          "cached": false,
          "cacheKey": null,
          "guName": null,
          "arrestRate": 0.0,
          "dataFound": false,
          "executionTimeNs": 295000,
          "errorMessage": null,
          "success": true
        },
        "amenityApiResult": {
          "cached": false,
          "cacheKey": "amenity:37.4979:127.0276:500",
          "categoryCount": 15,
          "placesByCategory": {
            "CT1": 12,
            "AT4": 4,
            "CS2": 15,
            "SC4": 1,
            "MT1": 1,
            "BK9": 15,
            "HP8": 15,
            "AC5": 15,
            "CE7": 15,
            "SW8": 2,
            "PO3": 1,
            "FD6": 15,
            "PK6": 15,
            "OL7": 0,
            "PM9": 15
          },
          "totalPlaces": 141,
          "responseSize": 16415,
          "executionTimeNs": 1073842800,
          "errorMessage": null,
          "success": true
        },
        "errorMessage": null,
        "success": true
      }
    },
    {
      "timestamp": "2025-11-21T10:20:44.259703700Z",
      "nanoTime": 26030273584100,
      "traceId": "41a9f7d4",
      "thread": "http-nio-8185-exec-3",
      "eventType": "PERFORMANCE",
      "step": "R-04",
      "layer": "Service",
      "class": "LocationAnalysisServiceImpl",
      "method": "performExternalApiCalls",
      "action": "performExternalApiCalls",
      "status": "START"
    },
    {
      "timestamp": "2025-11-21T10:20:45.483619300Z",
      "nanoTime": 26031498163000,
      "traceId": "41a9f7d4",
      "thread": "http-nio-8185-exec-3",
      "eventType": "PERFORMANCE",
      "step": "R-04",
      "layer": "Service",
      "class": "LocationAnalysisServiceImpl",
      "method": "performExternalApiCalls",
      "action": "performExternalApiCalls",
      "status": "END",
      "duration_ns": 1224578900,
      "duration_ms": 1224,
      "resultData": {
        "latitude": 37.5547,
        "longitude": 126.9707,
        "radius": 500,
        "totalSequentialTasks": 3,
        "totalExecutionTimeNs": 1224359800,
        "addressApiResult": {
          "cached": false,
          "cacheKey": "address:37.5547:126.9707",
          "roadAddress": "서울특별시 중구 한강대로 405",
          "jibunAddress": "서울 중구 봉래동2가 122-11",
          "responseSize": 73,
          "executionTimeNs": 96109200,
          "errorMessage": null,
          "success": true
        },
        "arrestRateResult": {
          "cached": false,
          "cacheKey": "arrest_rate:중구",
          "guName": "중구",
          "arrestRate": 0.866910799,
          "dataFound": true,
          "executionTimeNs": 16230100,
          "errorMessage": null,
          "success": true
        },
        "amenityApiResult": {
          "cached": false,
          "cacheKey": "amenity:37.5547:126.9707:500",
          "categoryCount": 15,
          "placesByCategory": {
            "CT1": 9,
            "AT4": 1,
            "CS2": 15,
            "SC4": 1,
            "MT1": 2,
            "BK9": 15,
            "HP8": 15,
            "AC5": 13,
            "CE7": 15,
            "SW8": 5,
            "PO3": 8,
            "FD6": 15,
            "PK6": 15,
            "OL7": 2,
            "PM9": 8
          },
          "totalPlaces": 139,
          "responseSize": 16203,
          "executionTimeNs": 1112020500,
          "errorMessage": null,
          "success": true
        },
        "errorMessage": null,
        "success": true
      }
    },
    {
      "timestamp": "2025-11-21T10:20:51.944203900Z",
      "nanoTime": 26037958268100,
      "traceId": "bc578820",
      "thread": "http-nio-8185-exec-5",
      "eventType": "PERFORMANCE",
      "step": "R-04",
      "layer": "Service",
      "class": "LocationAnalysisServiceImpl",
      "method": "performExternalApiCalls",
      "action": "performExternalApiCalls",
      "status": "START"
    },
    {
      "timestamp": "2025-11-21T10:20:53.120128200Z",
      "nanoTime": 26039134472900,
      "traceId": "bc578820",
      "thread": "http-nio-8185-exec-5",
      "eventType": "PERFORMANCE",
      "step": "R-04",
      "layer": "Service",
      "class": "LocationAnalysisServiceImpl",
      "method": "performExternalApiCalls",
      "action": "performExternalApiCalls",
      "status": "END",
      "duration_ns": 1176204800,
      "duration_ms": 1176,
      "resultData": {
        "latitude": 37.5572,
        "longitude": 126.9239,
        "radius": 500,
        "totalSequentialTasks": 3,
        "totalExecutionTimeNs": 1175934400,
        "addressApiResult": {
          "cached": false,
          "cacheKey": "address:37.5572:126.9239",
          "roadAddress": "주소 없음",
          "jibunAddress": "서울 마포구 동교동 192-44",
          "responseSize": 60,
          "executionTimeNs": 111830400,
          "errorMessage": null,
          "success": true
        },
        "arrestRateResult": {
          "cached": false,
          "cacheKey": null,
          "guName": null,
          "arrestRate": 0.0,
          "dataFound": false,
          "executionTimeNs": 55300,
          "errorMessage": null,
          "success": true
        },
        "amenityApiResult": {
          "cached": false,
          "cacheKey": "amenity:37.5572:126.9239:500",
          "categoryCount": 15,
          "placesByCategory": {
            "CT1": 15,
            "AT4": 10,
            "CS2": 15,
            "SC4": 1,
            "MT1": 1,
            "BK9": 15,
            "HP8": 15,
            "AC5": 15,
            "CE7": 15,
            "SW8": 3,
            "PO3": 3,
            "FD6": 15,
            "PK6": 15,
            "OL7": 1,
            "PM9": 15
          },
          "totalPlaces": 154,
          "responseSize": 17877,
          "executionTimeNs": 1064048700,
          "errorMessage": null,
          "success": true
        },
        "errorMessage": null,
        "success": true
      }
    },
    {
      "timestamp": "2025-11-21T10:20:58.554043700Z",
      "nanoTime": 26044568446900,
      "traceId": "2d99f17e",
      "thread": "http-nio-8185-exec-6",
      "eventType": "PERFORMANCE",
      "step": "R-04",
      "layer": "Service",
      "class": "LocationAnalysisServiceImpl",
      "method": "performExternalApiCalls",
      "action": "performExternalApiCalls",
      "status": "START"
    },
    {
      "timestamp": "2025-11-21T10:20:59.791490300Z",
      "nanoTime": 26045805937000,
      "traceId": "2d99f17e",
      "thread": "http-nio-8185-exec-6",
      "eventType": "PERFORMANCE",
      "step": "R-04",
      "layer": "Service",
      "class": "LocationAnalysisServiceImpl",
      "method": "performExternalApiCalls",
      "action": "performExternalApiCalls",
      "status": "END",
      "duration_ns": 1237490100,
      "duration_ms": 1237,
      "resultData": {
        "latitude": 37.5326,
        "longitude": 126.9135,
        "radius": 500,
        "totalSequentialTasks": 3,
        "totalExecutionTimeNs": 1237276000,
        "addressApiResult": {
          "cached": false,
          "cacheKey": "address:37.5326:126.9135",
          "roadAddress": "서울특별시 영등포구 의사당대로 1",
          "jibunAddress": "서울 영등포구 여의도동 1",
          "responseSize": 70,
          "executionTimeNs": 61138300,
          "errorMessage": null,
          "success": true
        },
        "arrestRateResult": {
          "cached": false,
          "cacheKey": "arrest_rate:영등포구",
          "guName": "영등포구",
          "arrestRate": 0.721231491,
          "dataFound": true,
          "executionTimeNs": 4168900,
          "errorMessage": null,
          "success": true
        },
        "amenityApiResult": {
          "cached": false,
          "cacheKey": "amenity:37.5326:126.9135:500",
          "categoryCount": 15,
          "placesByCategory": {
            "CT1": 1,
            "AT4": 9,
            "CS2": 0,
            "SC4": 0,
            "MT1": 1,
            "BK9": 14,
            "HP8": 2,
            "AC5": 0,
            "CE7": 4,
            "SW8": 0,
            "PO3": 0,
            "FD6": 9,
            "PK6": 6,
            "OL7": 0,
            "PM9": 1
          },
          "totalPlaces": 47,
          "responseSize": 5608,
          "executionTimeNs": 1171968800,
          "errorMessage": null,
          "success": true
        },
        "errorMessage": null,
        "success": true
      }
    },
    {
      "timestamp": "2025-11-21T10:21:04.823618600Z",
      "nanoTime": 26050838023800,
      "traceId": "b3c73500",
      "thread": "http-nio-8185-exec-8",
      "eventType": "PERFORMANCE",
      "step": "R-04",
      "layer": "Service",
      "class": "LocationAnalysisServiceImpl",
      "method": "performExternalApiCalls",
      "action": "performExternalApiCalls",
      "status": "START"
    },
    {
      "timestamp": "2025-11-21T10:21:06.040671500Z",
      "nanoTime": 26052055406500,
      "traceId": "b3c73500",
      "thread": "http-nio-8185-exec-8",
      "eventType": "PERFORMANCE",
      "step": "R-04",
      "layer": "Service",
      "class": "LocationAnalysisServiceImpl",
      "method": "performExternalApiCalls",
      "action": "performExternalApiCalls",
      "status": "END",
      "duration_ns": 1217382700,
      "duration_ms": 1217,
      "resultData": {
        "latitude": 37.5133,
        "longitude": 127.1,
        "radius": 500,
        "totalSequentialTasks": 3,
        "totalExecutionTimeNs": 1217186600,
        "addressApiResult": {
          "cached": false,
          "cacheKey": "address:37.5133:127.1",
          "roadAddress": "서울특별시 송파구 올림픽로 지하 265",
          "jibunAddress": "서울 송파구 신천동 8",
          "responseSize": 71,
          "executionTimeNs": 99805900,
          "errorMessage": null,
          "success": true
        },
        "arrestRateResult": {
          "cached": false,
          "cacheKey": "arrest_rate:송파구",
          "guName": "송파구",
          "arrestRate": 0.657451864,
          "dataFound": true,
          "executionTimeNs": 4979700,
          "errorMessage": null,
          "success": true
        },
        "amenityApiResult": {
          "cached": false,
          "cacheKey": "amenity:37.5133:127.1:500",
          "categoryCount": 15,
          "placesByCategory": {
            "CT1": 15,
            "AT4": 5,
            "CS2": 15,
            "SC4": 2,
            "MT1": 4,
            "BK9": 15,
            "HP8": 15,
            "AC5": 15,
            "CE7": 15,
            "SW8": 2,
            "PO3": 2,
            "FD6": 15,
            "PK6": 15,
            "OL7": 0,
            "PM9": 15
          },
          "totalPlaces": 150,
          "responseSize": 17627,
          "executionTimeNs": 1112401000,
          "errorMessage": null,
          "success": true
        },
        "errorMessage": null,
        "success": true
      }
    },
    {
      "timestamp": "2025-11-21T10:21:09.396622200Z",
      "nanoTime": 26055410623700,
      "traceId": "19522106",
      "thread": "http-nio-8185-exec-4",
      "eventType": "PERFORMANCE",
      "step": "R-04",
      "layer": "Service",
      "class": "LocationAnalysisServiceImpl",
      "method": "performExternalApiCalls",
      "action": "performExternalApiCalls",
      "status": "START"
    },
    {
      "timestamp": "2025-11-21T10:21:10.600881Z",
      "nanoTime": 26056615307800,
      "traceId": "19522106",
      "thread": "http-nio-8185-exec-4",
      "eventType": "PERFORMANCE",
      "step": "R-04",
      "layer": "Service",
      "class": "LocationAnalysisServiceImpl",
      "method": "performExternalApiCalls",
      "action": "performExternalApiCalls",
      "status": "END",
      "duration_ns": 1204684100,
      "duration_ms": 1204,
      "resultData": {
        "latitude": 37.5637,
        "longitude": 126.983,
        "radius": 500,
        "totalSequentialTasks": 3,
        "totalExecutionTimeNs": 1204522000,
        "addressApiResult": {
          "cached": false,
          "cacheKey": "address:37.5637:126.983",
          "roadAddress": "주소 없음",
          "jibunAddress": "서울 중구 명동1가 54-19",
          "responseSize": 59,
          "executionTimeNs": 74928000,
          "errorMessage": null,
          "success": true
        },
        "arrestRateResult": {
          "cached": false,
          "cacheKey": null,
          "guName": null,
          "arrestRate": 0.0,
          "dataFound": false,
          "executionTimeNs": 30100,
          "errorMessage": null,
          "success": true
        },
        "amenityApiResult": {
          "cached": false,
          "cacheKey": "amenity:37.5637:126.983:500",
          "categoryCount": 15,
          "placesByCategory": {
            "CT1": 15,
            "AT4": 6,
            "CS2": 15,
            "SC4": 0,
            "MT1": 0,
            "BK9": 15,
            "HP8": 15,
            "AC5": 15,
            "CE7": 15,
            "SW8": 2,
            "PO3": 15,
            "FD6": 15,
            "PK6": 15,
            "OL7": 0,
            "PM9": 15
          },
          "totalPlaces": 158,
          "responseSize": 18282,
          "executionTimeNs": 1129563900,
          "errorMessage": null,
          "success": true
        },
        "errorMessage": null,
        "success": true
      }
    },
    {
      "timestamp": "2025-11-21T10:21:17.237035500Z",
      "nanoTime": 26063251107900,
      "traceId": "d5730568",
      "thread": "http-nio-8185-exec-9",
      "eventType": "PERFORMANCE",
      "step": "R-04",
      "layer": "Service",
      "class": "LocationAnalysisServiceImpl",
      "method": "performExternalApiCalls",
      "action": "performExternalApiCalls",
      "status": "START"
    },
    {
      "timestamp": "2025-11-21T10:21:18.451499100Z",
      "nanoTime": 26064465816200,
      "traceId": "d5730568",
      "thread": "http-nio-8185-exec-9",
      "eventType": "PERFORMANCE",
      "step": "R-04",
      "layer": "Service",
      "class": "LocationAnalysisServiceImpl",
      "method": "performExternalApiCalls",
      "action": "performExternalApiCalls",
      "status": "END",
      "duration_ns": 1214708300,
      "duration_ms": 1214,
      "resultData": {
        "latitude": 37.5559,
        "longitude": 126.9368,
        "radius": 500,
        "totalSequentialTasks": 3,
        "totalExecutionTimeNs": 1214560000,
        "addressApiResult": {
          "cached": false,
          "cacheKey": "address:37.5559:126.9368",
          "roadAddress": "주소 없음",
          "jibunAddress": "서울 서대문구 창천동 30-16",
          "responseSize": 60,
          "executionTimeNs": 109256700,
          "errorMessage": null,
          "success": true
        },
        "arrestRateResult": {
          "cached": false,
          "cacheKey": null,
          "guName": null,
          "arrestRate": 0.0,
          "dataFound": false,
          "executionTimeNs": 37400,
          "errorMessage": null,
          "success": true
        },
        "amenityApiResult": {
          "cached": false,
          "cacheKey": "amenity:37.5559:126.9368:500",
          "categoryCount": 15,
          "placesByCategory": {
            "CT1": 15,
            "AT4": 4,
            "CS2": 15,
            "SC4": 3,
            "MT1": 3,
            "BK9": 15,
            "HP8": 15,
            "AC5": 15,
            "CE7": 15,
            "SW8": 2,
            "PO3": 4,
            "FD6": 15,
            "PK6": 15,
            "OL7": 0,
            "PM9": 15
          },
          "totalPlaces": 151,
          "responseSize": 17447,
          "executionTimeNs": 1105265900,
          "errorMessage": null,
          "success": true
        },
        "errorMessage": null,
        "success": true
      }
    },
    {
      "timestamp": "2025-11-21T10:21:23.765006Z",
      "nanoTime": 26069778958200,
      "traceId": "eb0bc93d",
      "thread": "http-nio-8185-exec-10",
      "eventType": "PERFORMANCE",
      "step": "R-04",
      "layer": "Service",
      "class": "LocationAnalysisServiceImpl",
      "method": "performExternalApiCalls",
      "action": "performExternalApiCalls",
      "status": "START"
    },
    {
      "timestamp": "2025-11-21T10:21:24.941122200Z",
      "nanoTime": 26070955235700,
      "traceId": "eb0bc93d",
      "thread": "http-nio-8185-exec-10",
      "eventType": "PERFORMANCE",
      "step": "R-04",
      "layer": "Service",
      "class": "LocationAnalysisServiceImpl",
      "method": "performExternalApiCalls",
      "action": "performExternalApiCalls",
      "status": "END",
      "duration_ns": 1176277500,
      "duration_ms": 1176,
      "resultData": {
        "latitude": 37.572,
        "longitude": 126.9769,
        "radius": 500,
        "totalSequentialTasks": 3,
        "totalExecutionTimeNs": 1176136400,
        "addressApiResult": {
          "cached": false,
          "cacheKey": "address:37.572:126.9769",
          "roadAddress": "서울특별시 종로구 세종대로 지하 175",
          "jibunAddress": "서울 종로구 세종로 81-3",
          "responseSize": 74,
          "executionTimeNs": 81962000,
          "errorMessage": null,
          "success": true
        },
        "arrestRateResult": {
          "cached": false,
          "cacheKey": "arrest_rate:종로구",
          "guName": "종로구",
          "arrestRate": 0.939777079,
          "dataFound": true,
          "executionTimeNs": 4753200,
          "errorMessage": null,
          "success": true
        },
        "amenityApiResult": {
          "cached": false,
          "cacheKey": "amenity:37.572:126.9769:500",
          "categoryCount": 15,
          "placesByCategory": {
            "CT1": 15,
            "AT4": 1,
            "CS2": 15,
            "SC4": 1,
            "MT1": 1,
            "BK9": 15,
            "HP8": 15,
            "AC5": 15,
            "CE7": 15,
            "SW8": 1,
            "PO3": 15,
            "FD6": 15,
            "PK6": 15,
            "OL7": 0,
            "PM9": 15
          },
          "totalPlaces": 154,
          "responseSize": 17820,
          "executionTimeNs": 1089421200,
          "errorMessage": null,
          "success": true
        },
        "errorMessage": null,
        "success": true
      }
    },
    {
      "timestamp": "2025-11-21T10:21:28.422035400Z",
      "nanoTime": 26074435882300,
      "traceId": "dbb24181",
      "thread": "http-nio-8185-exec-7",
      "eventType": "PERFORMANCE",
      "step": "R-04",
      "layer": "Service",
      "class": "LocationAnalysisServiceImpl",
      "method": "performExternalApiCalls",
      "action": "performExternalApiCalls",
      "status": "START"
    },
    {
      "timestamp": "2025-11-21T10:21:29.570718900Z",
      "nanoTime": 26075585037500,
      "traceId": "dbb24181",
      "thread": "http-nio-8185-exec-7",
      "eventType": "PERFORMANCE",
      "step": "R-04",
      "layer": "Service",
      "class": "LocationAnalysisServiceImpl",
      "method": "performExternalApiCalls",
      "action": "performExternalApiCalls",
      "status": "END",
      "duration_ns": 1149155200,
      "duration_ms": 1149,
      "resultData": {
        "latitude": 37.5403,
        "longitude": 127.0695,
        "radius": 500,
        "totalSequentialTasks": 3,
        "totalExecutionTimeNs": 1148927000,
        "addressApiResult": {
          "cached": false,
          "cacheKey": "address:37.5403:127.0695",
          "roadAddress": "서울특별시 광진구 아차산로 243",
          "jibunAddress": "서울 광진구 화양동 7-3",
          "responseSize": 70,
          "executionTimeNs": 72886300,
          "errorMessage": null,
          "success": true
        },
        "arrestRateResult": {
          "cached": false,
          "cacheKey": "arrest_rate:광진구",
          "guName": "광진구",
          "arrestRate": 0.672940923,
          "dataFound": true,
          "executionTimeNs": 5397200,
          "errorMessage": null,
          "success": true
        },
        "amenityApiResult": {
          "cached": false,
          "cacheKey": "amenity:37.5403:127.0695:500",
          "categoryCount": 15,
          "placesByCategory": {
            "CT1": 10,
            "AT4": 4,
            "CS2": 15,
            "SC4": 0,
            "MT1": 2,
            "BK9": 15,
            "HP8": 15,
            "AC5": 15,
            "CE7": 15,
            "SW8": 2,
            "PO3": 0,
            "FD6": 15,
            "PK6": 15,
            "OL7": 0,
            "PM9": 15
          },
          "totalPlaces": 138,
          "responseSize": 16047,
          "executionTimeNs": 1070643500,
          "errorMessage": null,
          "success": true
        },
        "errorMessage": null,
        "success": true
      }
    },
    {
      "timestamp": "2025-11-21T10:21:34.035320300Z",
      "nanoTime": 26080049394800,
      "traceId": "e17c84a0",
      "thread": "http-nio-8185-exec-1",
      "eventType": "PERFORMANCE",
      "step": "R-04",
      "layer": "Service",
      "class": "LocationAnalysisServiceImpl",
      "method": "performExternalApiCalls",
      "action": "performExternalApiCalls",
      "status": "START"
    },
    {
      "timestamp": "2025-11-21T10:21:35.172959400Z",
      "nanoTime": 26081187343500,
      "traceId": "e17c84a0",
      "thread": "http-nio-8185-exec-1",
      "eventType": "PERFORMANCE",
      "step": "R-04",
      "layer": "Service",
      "class": "LocationAnalysisServiceImpl",
      "method": "performExternalApiCalls",
      "action": "performExternalApiCalls",
      "status": "END",
      "duration_ns": 1137948700,
      "duration_ms": 1137,
      "resultData": {
        "latitude": 37.5344,
        "longitude": 126.9944,
        "radius": 500,
        "totalSequentialTasks": 3,
        "totalExecutionTimeNs": 1137828500,
        "addressApiResult": {
          "cached": false,
          "cacheKey": "address:37.5344:126.9944",
          "roadAddress": "주소 없음",
          "jibunAddress": "서울 용산구 이태원동 127-10",
          "responseSize": 61,
          "executionTimeNs": 66207300,
          "errorMessage": null,
          "success": true
        },
        "arrestRateResult": {
          "cached": false,
          "cacheKey": null,
          "guName": null,
          "arrestRate": 0.0,
          "dataFound": false,
          "executionTimeNs": 35200,
          "errorMessage": null,
          "success": true
        },
        "amenityApiResult": {
          "cached": false,
          "cacheKey": "amenity:37.5344:126.9944:500",
          "categoryCount": 15,
          "placesByCategory": {
            "CT1": 15,
            "AT4": 7,
            "CS2": 15,
            "SC4": 1,
            "MT1": 0,
            "BK9": 15,
            "HP8": 15,
            "AC5": 14,
            "CE7": 15,
            "SW8": 1,
            "PO3": 15,
            "FD6": 15,
            "PK6": 15,
            "OL7": 0,
            "PM9": 5
          },
          "totalPlaces": 148,
          "responseSize": 17040,
          "executionTimeNs": 1071586000,
          "errorMessage": null,
          "success": true
        },
        "errorMessage": null,
        "success": true
      }
    },
    {
      "timestamp": "2025-11-21T10:21:39.557546800Z",
      "nanoTime": 26085571943400,
      "traceId": "4e4be05b",
      "thread": "http-nio-8185-exec-2",
      "eventType": "PERFORMANCE",
      "step": "R-04",
      "layer": "Service",
      "class": "LocationAnalysisServiceImpl",
      "method": "performExternalApiCalls",
      "action": "performExternalApiCalls",
      "status": "START"
    },
    {
      "timestamp": "2025-11-21T10:21:40.720030100Z",
      "nanoTime": 26086734264500,
      "traceId": "4e4be05b",
      "thread": "http-nio-8185-exec-2",
      "eventType": "PERFORMANCE",
      "step": "R-04",
      "layer": "Service",
      "class": "LocationAnalysisServiceImpl",
      "method": "performExternalApiCalls",
      "action": "performExternalApiCalls",
      "status": "END",
      "duration_ns": 1162321100,
      "duration_ms": 1162,
      "resultData": {
        "latitude": 37.5446,
        "longitude": 127.0558,
        "radius": 500,
        "totalSequentialTasks": 3,
        "totalExecutionTimeNs": 1162170500,
        "addressApiResult": {
          "cached": false,
          "cacheKey": "address:37.5446:127.0558",
          "roadAddress": "서울특별시 성동구 아차산로 100",
          "jibunAddress": "서울 성동구 성수동2가 300-1",
          "responseSize": 74,
          "executionTimeNs": 59028000,
          "errorMessage": null,
          "success": true
        },
        "arrestRateResult": {
          "cached": false,
          "cacheKey": "arrest_rate:성동구",
          "guName": "성동구",
          "arrestRate": 0.745164096,
          "dataFound": true,
          "executionTimeNs": 3724500,
          "errorMessage": null,
          "success": true
        },
        "amenityApiResult": {
          "cached": false,
          "cacheKey": "amenity:37.5446:127.0558:500",
          "categoryCount": 15,
          "placesByCategory": {
            "CT1": 15,
            "AT4": 4,
            "CS2": 15,
            "SC4": 0,
            "MT1": 1,
            "BK9": 15,
            "HP8": 15,
            "AC5": 15,
            "CE7": 15,
            "SW8": 1,
            "PO3": 3,
            "FD6": 15,
            "PK6": 15,
            "OL7": 1,
            "PM9": 8
          },
          "totalPlaces": 138,
          "responseSize": 15916,
          "executionTimeNs": 1099418000,
          "errorMessage": null,
          "success": true
        },
        "errorMessage": null,
        "success": true
      }
    },
    {
      "timestamp": "2025-11-21T10:21:43.961045400Z",
      "nanoTime": 26089974888800,
      "traceId": "d88f87e7",
      "thread": "http-nio-8185-exec-3",
      "eventType": "PERFORMANCE",
      "step": "R-04",
      "layer": "Service",
      "class": "LocationAnalysisServiceImpl",
      "method": "performExternalApiCalls",
      "action": "performExternalApiCalls",
      "status": "START"
    },
    {
      "timestamp": "2025-11-21T10:21:45.229009Z",
      "nanoTime": 26091243731600,
      "traceId": "d88f87e7",
      "thread": "http-nio-8185-exec-3",
      "eventType": "PERFORMANCE",
      "step": "R-04",
      "layer": "Service",
      "class": "LocationAnalysisServiceImpl",
      "method": "performExternalApiCalls",
      "action": "performExternalApiCalls",
      "status": "END",
      "duration_ns": 1268842800,
      "duration_ms": 1268,
      "resultData": {
        "latitude": 37.5709,
        "longitude": 126.992,
        "radius": 500,
        "totalSequentialTasks": 3,
        "totalExecutionTimeNs": 1268684200,
        "addressApiResult": {
          "cached": false,
          "cacheKey": "address:37.5709:126.992",
          "roadAddress": "주소 없음",
          "jibunAddress": "서울 종로구 묘동 20-5",
          "responseSize": 57,
          "executionTimeNs": 79849400,
          "errorMessage": null,
          "success": true
        },
        "arrestRateResult": {
          "cached": false,
          "cacheKey": null,
          "guName": null,
          "arrestRate": 0.0,
          "dataFound": false,
          "executionTimeNs": 38400,
          "errorMessage": null,
          "success": true
        },
        "amenityApiResult": {
          "cached": false,
          "cacheKey": "amenity:37.5709:126.992:500",
          "categoryCount": 15,
          "placesByCategory": {
            "CT1": 15,
            "AT4": 14,
            "CS2": 15,
            "SC4": 0,
            "MT1": 0,
            "BK9": 15,
            "HP8": 15,
            "AC5": 15,
            "CE7": 15,
            "SW8": 4,
            "PO3": 5,
            "FD6": 15,
            "PK6": 15,
            "OL7": 0,
            "PM9": 9
          },
          "totalPlaces": 152,
          "responseSize": 17628,
          "executionTimeNs": 1188796400,
          "errorMessage": null,
          "success": true
        },
        "errorMessage": null,
        "success": true
      }
    },
    {
      "timestamp": "2025-11-21T10:21:48.456146Z",
      "nanoTime": 26094470219700,
      "traceId": "6f4d9b6e",
      "thread": "http-nio-8185-exec-5",
      "eventType": "PERFORMANCE",
      "step": "R-04",
      "layer": "Service",
      "class": "LocationAnalysisServiceImpl",
      "method": "performExternalApiCalls",
      "action": "performExternalApiCalls",
      "status": "START"
    },
    {
      "timestamp": "2025-11-21T10:21:49.653913800Z",
      "nanoTime": 26095668563800,
      "traceId": "6f4d9b6e",
      "thread": "http-nio-8185-exec-5",
      "eventType": "PERFORMANCE",
      "step": "R-04",
      "layer": "Service",
      "class": "LocationAnalysisServiceImpl",
      "method": "performExternalApiCalls",
      "action": "performExternalApiCalls",
      "status": "END",
      "duration_ns": 1198344100,
      "duration_ms": 1198,
      "resultData": {
        "latitude": 37.5276,
        "longitude": 127.0397,
        "radius": 500,
        "totalSequentialTasks": 3,
        "totalExecutionTimeNs": 1198208400,
        "addressApiResult": {
          "cached": false,
          "cacheKey": "address:37.5276:127.0397",
          "roadAddress": "주소 없음",
          "jibunAddress": "서울 강남구 신사동 668-33",
          "responseSize": 60,
          "executionTimeNs": 112521300,
          "errorMessage": null,
          "success": true
        },
        "arrestRateResult": {
          "cached": false,
          "cacheKey": null,
          "guName": null,
          "arrestRate": 0.0,
          "dataFound": false,
          "executionTimeNs": 42300,
          "errorMessage": null,
          "success": true
        },
        "amenityApiResult": {
          "cached": false,
          "cacheKey": "amenity:37.5276:127.0397:500",
          "categoryCount": 15,
          "placesByCategory": {
            "CT1": 15,
            "AT4": 6,
            "CS2": 15,
            "SC4": 2,
            "MT1": 2,
            "BK9": 15,
            "HP8": 15,
            "AC5": 15,
            "CE7": 15,
            "SW8": 1,
            "PO3": 1,
            "FD6": 15,
            "PK6": 15,
            "OL7": 0,
            "PM9": 14
          },
          "totalPlaces": 146,
          "responseSize": 16938,
          "executionTimeNs": 1085644800,
          "errorMessage": null,
          "success": true
        },
        "errorMessage": null,
        "success": true
      }
    },
    {
      "timestamp": "2025-11-21T10:21:52.902507400Z",
      "nanoTime": 26098916468400,
      "traceId": "da141549",
      "thread": "http-nio-8185-exec-6",
      "eventType": "PERFORMANCE",
      "step": "R-04",
      "layer": "Service",
      "class": "LocationAnalysisServiceImpl",
      "method": "performExternalApiCalls",
      "action": "performExternalApiCalls",
      "status": "START"
    },
    {
      "timestamp": "2025-11-21T10:21:54.039976500Z",
      "nanoTime": 26100054101700,
      "traceId": "da141549",
      "thread": "http-nio-8185-exec-6",
      "eventType": "PERFORMANCE",
      "step": "R-04",
      "layer": "Service",
      "class": "LocationAnalysisServiceImpl",
      "method": "performExternalApiCalls",
      "action": "performExternalApiCalls",
      "status": "END",
      "duration_ns": 1137633300,
      "duration_ms": 1137,
      "resultData": {
        "latitude": 37.5087,
        "longitude": 127.0633,
        "radius": 500,
        "totalSequentialTasks": 3,
        "totalExecutionTimeNs": 1137477400,
        "addressApiResult": {
          "cached": false,
          "cacheKey": "address:37.5087:127.0633",
          "roadAddress": "주소 없음",
          "jibunAddress": "서울 강남구 대치동 1011",
          "responseSize": 58,
          "executionTimeNs": 99604100,
          "errorMessage": null,
          "success": true
        },
        "arrestRateResult": {
          "cached": false,
          "cacheKey": null,
          "guName": null,
          "arrestRate": 0.0,
          "dataFound": false,
          "executionTimeNs": 58200,
          "errorMessage": null,
          "success": true
        },
        "amenityApiResult": {
          "cached": false,
          "cacheKey": "amenity:37.5087:127.0633:500",
          "categoryCount": 15,
          "placesByCategory": {
            "CT1": 15,
            "AT4": 1,
            "CS2": 15,
            "SC4": 3,
            "MT1": 0,
            "BK9": 15,
            "HP8": 15,
            "AC5": 15,
            "CE7": 15,
            "SW8": 1,
            "PO3": 5,
            "FD6": 15,
            "PK6": 15,
            "OL7": 1,
            "PM9": 12
          },
          "totalPlaces": 143,
          "responseSize": 16733,
          "executionTimeNs": 1037815100,
          "errorMessage": null,
          "success": true
        },
        "errorMessage": null,
        "success": true
      }
    },
    {
      "timestamp": "2025-11-21T10:21:57.042008900Z",
      "nanoTime": 26103055969000,
      "traceId": "2d850537",
      "thread": "http-nio-8185-exec-8",
      "eventType": "PERFORMANCE",
      "step": "R-04",
      "layer": "Service",
      "class": "LocationAnalysisServiceImpl",
      "method": "performExternalApiCalls",
      "action": "performExternalApiCalls",
      "status": "START"
    },
    {
      "timestamp": "2025-11-21T10:21:58.199884500Z",
      "nanoTime": 26104214128100,
      "traceId": "2d850537",
      "thread": "http-nio-8185-exec-8",
      "eventType": "PERFORMANCE",
      "step": "R-04",
      "layer": "Service",
      "class": "LocationAnalysisServiceImpl",
      "method": "performExternalApiCalls",
      "action": "performExternalApiCalls",
      "status": "END",
      "duration_ns": 1158159100,
      "duration_ms": 1158,
      "resultData": {
        "latitude": 37.5612,
        "longitude": 127.0377,
        "radius": 500,
        "totalSequentialTasks": 3,
        "totalExecutionTimeNs": 1158028300,
        "addressApiResult": {
          "cached": false,
          "cacheKey": "address:37.5612:127.0377",
          "roadAddress": "주소 없음",
          "jibunAddress": "서울 성동구 행당동 168-151",
          "responseSize": 61,
          "executionTimeNs": 81812100,
          "errorMessage": null,
          "success": true
        },
        "arrestRateResult": {
          "cached": false,
          "cacheKey": null,
          "guName": null,
          "arrestRate": 0.0,
          "dataFound": false,
          "executionTimeNs": 34200,
          "errorMessage": null,
          "success": true
        },
        "amenityApiResult": {
          "cached": false,
          "cacheKey": "amenity:37.5612:127.0377:500",
          "categoryCount": 15,
          "placesByCategory": {
            "CT1": 6,
            "AT4": 3,
            "CS2": 15,
            "SC4": 3,
            "MT1": 3,
            "BK9": 15,
            "HP8": 15,
            "AC5": 15,
            "CE7": 15,
            "SW8": 4,
            "PO3": 7,
            "FD6": 15,
            "PK6": 15,
            "OL7": 1,
            "PM9": 15
          },
          "totalPlaces": 147,
          "responseSize": 17057,
          "executionTimeNs": 1076182000,
          "errorMessage": null,
          "success": true
        },
        "errorMessage": null,
        "success": true
      }
    },
    {
      "timestamp": "2025-11-21T10:22:01.750483200Z",
      "nanoTime": 26107764901100,
      "traceId": "a20b9902",
      "thread": "http-nio-8185-exec-4",
      "eventType": "PERFORMANCE",
      "step": "R-04",
      "layer": "Service",
      "class": "LocationAnalysisServiceImpl",
      "method": "performExternalApiCalls",
      "action": "performExternalApiCalls",
      "status": "START"
    },
    {
      "timestamp": "2025-11-21T10:22:02.947092Z",
      "nanoTime": 26108960978100,
      "traceId": "a20b9902",
      "thread": "http-nio-8185-exec-4",
      "eventType": "PERFORMANCE",
      "step": "R-04",
      "layer": "Service",
      "class": "LocationAnalysisServiceImpl",
      "method": "performExternalApiCalls",
      "action": "performExternalApiCalls",
      "status": "END",
      "duration_ns": 1196077000,
      "duration_ms": 1196,
      "resultData": {
        "latitude": 37.4764,
        "longitude": 126.9814,
        "radius": 500,
        "totalSequentialTasks": 3,
        "totalExecutionTimeNs": 1195930100,
        "addressApiResult": {
          "cached": false,
          "cacheKey": "address:37.4764:126.9814",
          "roadAddress": "주소 없음",
          "jibunAddress": "서울 관악구 남현동 1130-1",
          "responseSize": 60,
          "executionTimeNs": 78206200,
          "errorMessage": null,
          "success": true
        },
        "arrestRateResult": {
          "cached": false,
          "cacheKey": null,
          "guName": null,
          "arrestRate": 0.0,
          "dataFound": false,
          "executionTimeNs": 45500,
          "errorMessage": null,
          "success": true
        },
        "amenityApiResult": {
          "cached": false,
          "cacheKey": "amenity:37.4764:126.9814:500",
          "categoryCount": 15,
          "placesByCategory": {
            "CT1": 5,
            "AT4": 3,
            "CS2": 15,
            "SC4": 1,
            "MT1": 1,
            "BK9": 15,
            "HP8": 15,
            "AC5": 15,
            "CE7": 15,
            "SW8": 2,
            "PO3": 3,
            "FD6": 15,
            "PK6": 15,
            "OL7": 2,
            "PM9": 15
          },
          "totalPlaces": 137,
          "responseSize": 15882,
          "executionTimeNs": 1117678400,
          "errorMessage": null,
          "success": true
        },
        "errorMessage": null,
        "success": true
      }
    },
    {
      "timestamp": "2025-11-21T10:22:06.700884Z",
      "nanoTime": 26112714696200,
      "traceId": "4d2b3d71",
      "thread": "http-nio-8185-exec-9",
      "eventType": "PERFORMANCE",
      "step": "R-04",
      "layer": "Service",
      "class": "LocationAnalysisServiceImpl",
      "method": "performExternalApiCalls",
      "action": "performExternalApiCalls",
      "status": "START"
    },
    {
      "timestamp": "2025-11-21T10:22:07.941641600Z",
      "nanoTime": 26113955591600,
      "traceId": "4d2b3d71",
      "thread": "http-nio-8185-exec-9",
      "eventType": "PERFORMANCE",
      "step": "R-04",
      "layer": "Service",
      "class": "LocationAnalysisServiceImpl",
      "method": "performExternalApiCalls",
      "action": "performExternalApiCalls",
      "status": "END",
      "duration_ns": 1240895400,
      "duration_ms": 1240,
      "resultData": {
        "latitude": 37.4815,
        "longitude": 126.8826,
        "radius": 500,
        "totalSequentialTasks": 3,
        "totalExecutionTimeNs": 1240760600,
        "addressApiResult": {
          "cached": false,
          "cacheKey": "address:37.4815:126.8826",
          "roadAddress": "서울특별시 금천구 벚꽃로 309",
          "jibunAddress": "서울 금천구 가산동 468-4",
          "responseSize": 71,
          "executionTimeNs": 82678700,
          "errorMessage": null,
          "success": true
        },
        "arrestRateResult": {
          "cached": false,
          "cacheKey": "arrest_rate:금천구",
          "guName": "금천구",
          "arrestRate": 0.715492589,
          "dataFound": true,
          "executionTimeNs": 4692400,
          "errorMessage": null,
          "success": true
        },
        "amenityApiResult": {
          "cached": false,
          "cacheKey": "amenity:37.4815:126.8826:500",
          "categoryCount": 15,
          "placesByCategory": {
            "CT1": 5,
            "AT4": 1,
            "CS2": 15,
            "SC4": 1,
            "MT1": 3,
            "BK9": 15,
            "HP8": 15,
            "AC5": 15,
            "CE7": 15,
            "SW8": 2,
            "PO3": 0,
            "FD6": 15,
            "PK6": 15,
            "OL7": 1,
            "PM9": 15
          },
          "totalPlaces": 133,
          "responseSize": 15515,
          "executionTimeNs": 1153389500,
          "errorMessage": null,
          "success": true
        },
        "errorMessage": null,
        "success": true
      }
    },
    {
      "timestamp": "2025-11-21T10:22:10.537455400Z",
      "nanoTime": 26116551366900,
      "traceId": "9d3e5d65",
      "thread": "http-nio-8185-exec-10",
      "eventType": "PERFORMANCE",
      "step": "R-04",
      "layer": "Service",
      "class": "LocationAnalysisServiceImpl",
      "method": "performExternalApiCalls",
      "action": "performExternalApiCalls",
      "status": "START"
    },
    {
      "timestamp": "2025-11-21T10:22:11.669034300Z",
      "nanoTime": 26117683304700,
      "traceId": "9d3e5d65",
      "thread": "http-nio-8185-exec-10",
      "eventType": "PERFORMANCE",
      "step": "R-04",
      "layer": "Service",
      "class": "LocationAnalysisServiceImpl",
      "method": "performExternalApiCalls",
      "action": "performExternalApiCalls",
      "status": "END",
      "duration_ns": 1131937800,
      "duration_ms": 1131,
      "resultData": {
        "latitude": 37.5245,
        "longitude": 126.896,
        "radius": 500,
        "totalSequentialTasks": 3,
        "totalExecutionTimeNs": 1131815900,
        "addressApiResult": {
          "cached": false,
          "cacheKey": "address:37.5245:126.896",
          "roadAddress": "서울특별시 영등포구 양산로 111",
          "jibunAddress": "서울 영등포구 당산동3가 370-4",
          "responseSize": 75,
          "executionTimeNs": 81911500,
          "errorMessage": null,
          "success": true
        },
        "arrestRateResult": {
          "cached": true,
          "cacheKey": "arrest_rate:영등포구",
          "guName": "영등포구",
          "arrestRate": 0.721231491,
          "dataFound": true,
          "executionTimeNs": 3760400,
          "errorMessage": null,
          "success": true
        },
        "amenityApiResult": {
          "cached": false,
          "cacheKey": "amenity:37.5245:126.896:500",
          "categoryCount": 15,
          "placesByCategory": {
            "CT1": 3,
            "AT4": 0,
            "CS2": 15,
            "SC4": 0,
            "MT1": 4,
            "BK9": 15,
            "HP8": 15,
            "AC5": 15,
            "CE7": 15,
            "SW8": 2,
            "PO3": 5,
            "FD6": 15,
            "PK6": 15,
            "OL7": 0,
            "PM9": 11
          },
          "totalPlaces": 130,
          "responseSize": 15121,
          "executionTimeNs": 1046144000,
          "errorMessage": null,
          "success": true
        },
        "errorMessage": null,
        "success": true
      }
    },
    {
      "timestamp": "2025-11-21T10:22:14.719663800Z",
      "nanoTime": 26120733657700,
      "traceId": "7aa00089",
      "thread": "http-nio-8185-exec-7",
      "eventType": "PERFORMANCE",
      "step": "R-04",
      "layer": "Service",
      "class": "LocationAnalysisServiceImpl",
      "method": "performExternalApiCalls",
      "action": "performExternalApiCalls",
      "status": "START"
    },
    {
      "timestamp": "2025-11-21T10:22:15.890045Z",
      "nanoTime": 26121904234500,
      "traceId": "7aa00089",
      "thread": "http-nio-8185-exec-7",
      "eventType": "PERFORMANCE",
      "step": "R-04",
      "layer": "Service",
      "class": "LocationAnalysisServiceImpl",
      "method": "performExternalApiCalls",
      "action": "performExternalApiCalls",
      "status": "END",
      "duration_ns": 1170576800,
      "duration_ms": 1170,
      "resultData": {
        "latitude": 37.5048,
        "longitude": 127.0491,
        "radius": 500,
        "totalSequentialTasks": 3,
        "totalExecutionTimeNs": 1170441000,
        "addressApiResult": {
          "cached": false,
          "cacheKey": "address:37.5048:127.0491",
          "roadAddress": "주소 없음",
          "jibunAddress": "서울 강남구 삼성동 172-66",
          "responseSize": 60,
          "executionTimeNs": 91523400,
          "errorMessage": null,
          "success": true
        },
        "arrestRateResult": {
          "cached": false,
          "cacheKey": null,
          "guName": null,
          "arrestRate": 0.0,
          "dataFound": false,
          "executionTimeNs": 36200,
          "errorMessage": null,
          "success": true
        },
        "amenityApiResult": {
          "cached": false,
          "cacheKey": "amenity:37.5048:127.0491:500",
          "categoryCount": 15,
          "placesByCategory": {
            "CT1": 5,
            "AT4": 0,
            "CS2": 15,
            "SC4": 3,
            "MT1": 0,
            "BK9": 15,
            "HP8": 15,
            "AC5": 15,
            "CE7": 15,
            "SW8": 2,
            "PO3": 0,
            "FD6": 15,
            "PK6": 15,
            "OL7": 0,
            "PM9": 15
          },
          "totalPlaces": 130,
          "responseSize": 15054,
          "executionTimeNs": 1078881400,
          "errorMessage": null,
          "success": true
        },
        "errorMessage": null,
        "success": true
      }
    },
    {
      "timestamp": "2025-11-21T10:22:18.643311700Z",
      "nanoTime": 26124657983800,
      "traceId": "b7201ab3",
      "thread": "http-nio-8185-exec-1",
      "eventType": "PERFORMANCE",
      "step": "R-04",
      "layer": "Service",
      "class": "LocationAnalysisServiceImpl",
      "method": "performExternalApiCalls",
      "action": "performExternalApiCalls",
      "status": "START"
    },
    {
      "timestamp": "2025-11-21T10:22:20.019889600Z",
      "nanoTime": 26126033865000,
      "traceId": "b7201ab3",
      "thread": "http-nio-8185-exec-1",
      "eventType": "PERFORMANCE",
      "step": "R-04",
      "layer": "Service",
      "class": "LocationAnalysisServiceImpl",
      "method": "performExternalApiCalls",
      "action": "performExternalApiCalls",
      "status": "END",
      "duration_ns": 1375881200,
      "duration_ms": 1375,
      "resultData": {
        "latitude": 37.4854,
        "longitude": 126.9013,
        "radius": 500,
        "totalSequentialTasks": 3,
        "totalExecutionTimeNs": 1375724400,
        "addressApiResult": {
          "cached": false,
          "cacheKey": "address:37.4854:126.9013",
          "roadAddress": "서울특별시 구로구 도림천로 477",
          "jibunAddress": "서울 구로구 구로동 810-3",
          "responseSize": 72,
          "executionTimeNs": 108179100,
          "errorMessage": null,
          "success": true
        },
        "arrestRateResult": {
          "cached": false,
          "cacheKey": "arrest_rate:구로구",
          "guName": "구로구",
          "arrestRate": 0.704705259,
          "dataFound": true,
          "executionTimeNs": 4306800,
          "errorMessage": null,
          "success": true
        },
        "amenityApiResult": {
          "cached": false,
          "cacheKey": "amenity:37.4854:126.9013:500",
          "categoryCount": 15,
          "placesByCategory": {
            "CT1": 3,
            "AT4": 3,
            "CS2": 15,
            "SC4": 1,
            "MT1": 1,
            "BK9": 15,
            "HP8": 15,
            "AC5": 15,
            "CE7": 15,
            "SW8": 1,
            "PO3": 2,
            "FD6": 15,
            "PK6": 15,
            "OL7": 1,
            "PM9": 14
          },
          "totalPlaces": 131,
          "responseSize": 15332,
          "executionTimeNs": 1263238500,
          "errorMessage": null,
          "success": true
        },
        "errorMessage": null,
        "success": true
      }
    }
  ]
}